src/ohmyprompt/__init__.py
src/ohmyprompt/cli.py
src/ohmyprompt/core/tools/__Init__.py
src/ohmyprompt/core/tools/base.py
src/ohmyprompt/core/tools/mypy_tool.py
src/ohmyprompt/core/tools/project_tools.py
src/ohmyprompt/core/tools/radon_tool.py
src/ohmyprompt/core/tools/ruff_tool.py
src/ohmyprompt/services/config_service.py
src/ohmyprompt/templates/report_template.md
src/ohmyprompt/utils/config_utils.py
src/ohmyprompt/utils/file_utils.py
src/ohmyprompt/utils/report_manager.py
src/ohmyprompt/utils/shell_utils.py
src/ohmyprompt/utils/formatters/__init__.py
src/ohmyprompt/utils/formatters/base.py
src/ohmyprompt/utils/formatters/formatter_factory.py
src/ohmyprompt/utils/formatters/mypy_formatter.py
src/ohmyprompt/utils/formatters/radon_formatter.py
src/ohmyprompt/utils/formatters/ruff_formatter.py
src/ohmyprompt/web/__init__.py
src/ohmyprompt/web/app.py
src/ohmyprompt/web/config_types.py
src/ohmyprompt/web/api/__init__.py
src/ohmyprompt/web/api/config.py
src/ohmyprompt/web/api/exclude.py
src/ohmyprompt/web/api/history.py
src/ohmyprompt/web/config/__init__.py
src/ohmyprompt/web/config/manager.py
src/ohmyprompt/web/config/mypy_config.py
src/ohmyprompt/web/config/radon_config.py
src/ohmyprompt/web/config/ruff_config.py
src/ohmyprompt/web/reports/web_report_manager.py
src/ohmyprompt/web/static/css/style.css
src/ohmyprompt/web/templates/index.html
ohmyprompt-0.1.5.dist-info/METADATA
ohmyprompt-0.1.5.dist-info/WHEEL
ohmyprompt-0.1.5.dist-info/entry_points.txt
ohmyprompt-0.1.5.dist-info/RECORD
